HiCPrediction/__init__.py
HiCPrediction/configurations.py
HiCPrediction/createAllTrainSets.py
HiCPrediction/createBaseFile.py
HiCPrediction/createTrainingSet.py
HiCPrediction/plotMatrix.py
HiCPrediction/predict.py
HiCPrediction/showFiles.py
HiCPrediction/tagCreator.py
HiCPrediction/test_createBaseFile.py
HiCPrediction/training.py
HiCPrediction_pkg/__init__.py
HiCPrediction_pkg/configurations.py
HiCPrediction_pkg/createAllTrainSets.py
HiCPrediction_pkg/createBaseFile.py
HiCPrediction_pkg/createTrainingSet.py
HiCPrediction_pkg/plotMatrix.py
HiCPrediction_pkg/predict.py
HiCPrediction_pkg/showFiles.py
HiCPrediction_pkg/tagCreator.py
HiCPrediction_pkg/test_createBaseFile.py
HiCPrediction_pkg/training.py
hiCPrediction_abajorat-0.0.1.data/scripts/createBaseFile.py
hiCPrediction_abajorat-0.0.1.data/scripts/createTrainingSet.py
hiCPrediction_abajorat-0.0.1.data/scripts/plotMatrix.py
hiCPrediction_abajorat-0.0.1.data/scripts/predict
hiCPrediction_abajorat-0.0.1.data/scripts/predict.py
hiCPrediction_abajorat-0.0.1.data/scripts/training.py
hiCPrediction_abajorat-0.0.1.dist-info/LICENSE
hiCPrediction_abajorat-0.0.1.dist-info/METADATA
hiCPrediction_abajorat-0.0.1.dist-info/WHEEL
hiCPrediction_abajorat-0.0.1.dist-info/top_level.txt
hiCPrediction_abajorat-0.0.1.dist-info/RECORD
